{
  "coverRasap": "",
  "coverBioenergeticsProgram": "",
  "coverCancerRehabilitation": "",
  "coverDiabetesProgram": "",
  "coverGastrointestinalProgram": "",
  "coverGeriatricsProgram": "",
  "coverHormonalRebalanceProgram": "",
  "coverOsteoporosisRehabilitation": "",
  "coverParkinsonsDisease": "",
  "coverRespiratoryHealth": "",
  "coverRheumatologicalRehabilitation": "",
  "coverSchoolHealth": "",
  "coverSleepCircadianRhythmClinic": "",
  "coverSpinalDeformityRehabilitation": "",
  "coverTravelMedicineClinic": ""
}